<?xml version="1.0" standalone="yes" ?>
<DBMODEL Version="4.0">
<SETTINGS>
<GLOBALSETTINGS ModelName="ordencompra" IDModel="0" IDVersion="0" VersionStr="1.0.0.0" Comments="" UseVersionHistroy="1" AutoIncVersion="1" DatabaseType="MySQL" ZoomFac="74.00" XPos="0" YPos="0" DefaultDataType="5" DefaultTablePrefix="0" DefSaveDBConn="" DefSyncDBConn="oc" DefQueryDBConn="" Printer="" HPageCount="4.0" PageAspectRatio="1.440892512336408" PageOrientation="1" PageFormat="A4 (210x297 mm, 8.26x11.7 inches)" SelectedPages="" UsePositionGrid="0" PositionGridX="20" PositionGridY="20" TableNameInRefs="0" DefaultTableType="0" ActivateRefDefForNewRelations="1" FKPrefix="" FKPostfix="" CreateFKRefDefIndex="1" DBQuoteCharacter="`" CreateSQLforLinkedObjects="0" DefModelFont="Tahoma" CanvasWidth="4096" CanvasHeight="2842" />
<DATATYPEGROUPS>
<DATATYPEGROUP Name="Numeric Types" Icon="1" />
<DATATYPEGROUP Name="Date and Time Types" Icon="2" />
<DATATYPEGROUP Name="String Types" Icon="3" />
<DATATYPEGROUP Name="Blob and Text Types" Icon="4" />
<DATATYPEGROUP Name="User defined Types" Icon="5" />
<DATATYPEGROUP Name="Geographic Types" Icon="6" />
</DATATYPEGROUPS>
<DATATYPES>
<DATATYPE ID="1" IDGroup="0" TypeName="TINYINT" Description="A very small integer. The signed range is -128 to 127. The unsigned range is 0 to 255." ParamCount="1" OptionCount="2" ParamRequired="0" EditParamsAsString="0" SynonymGroup="0" PhysicalMapping="0" PhysicalTypeName="" >
<PARAMS>
<PARAM Name="length" />
</PARAMS>
<OPTIONS>
<OPTION Name="UNSIGNED" Default="1" />
<OPTION Name="ZEROFILL" Default="0" />
</OPTIONS>
</DATATYPE>
<DATATYPE ID="2" IDGroup="0" TypeName="SMALLINT" Description="A small integer. The signed range is -32768 to 32767. The unsigned range is 0 to 65535." ParamCount="1" OptionCount="2" ParamRequired="0" EditParamsAsString="0" SynonymGroup="0" PhysicalMapping="0" PhysicalTypeName="" >
<PARAMS>
<PARAM Name="length" />
</PARAMS>
<OPTIONS>
<OPTION Name="UNSIGNED" Default="1" />
<OPTION Name="ZEROFILL" Default="0" />
</OPTIONS>
</DATATYPE>
<DATATYPE ID="3" IDGroup="0" TypeName="MEDIUMINT" Description="A medium-size integer. The signed range is -8388608 to 8388607. The unsigned range is 0 to 16777215." ParamCount="1" OptionCount="2" ParamRequired="0" EditParamsAsString="0" SynonymGroup="0" PhysicalMapping="0" PhysicalTypeName="" >
<PARAMS>
<PARAM Name="length" />
</PARAMS>
<OPTIONS>
<OPTION Name="UNSIGNED" Default="1" />
<OPTION Name="ZEROFILL" Default="0" />
</OPTIONS>
</DATATYPE>
<DATATYPE ID="4" IDGroup="0" TypeName="INT" Description="A normal-size integer. The signed range is -2147483648 to 2147483647. The unsigned range is 0 to 4294967295." ParamCount="1" OptionCount="2" ParamRequired="0" EditParamsAsString="0" SynonymGroup="1" PhysicalMapping="0" PhysicalTypeName="" >
<PARAMS>
<PARAM Name="length" />
</PARAMS>
<OPTIONS>
<OPTION Name="UNSIGNED" Default="0" />
<OPTION Name="ZEROFILL" Default="0" />
</OPTIONS>
</DATATYPE>
<DATATYPE ID="5" IDGroup="0" TypeName="INTEGER" Description="A normal-size integer. The signed range is -2147483648 to 2147483647. The unsigned range is 0 to 4294967295." ParamCount="1" OptionCount="2" ParamRequired="0" EditParamsAsString="0" SynonymGroup="1" PhysicalMapping="0" PhysicalTypeName="" >
<PARAMS>
<PARAM Name="length" />
</PARAMS>
<OPTIONS>
<OPTION Name="UNSIGNED" Default="1" />
<OPTION Name="ZEROFILL" Default="0" />
</OPTIONS>
</DATATYPE>
<DATATYPE ID="6" IDGroup="0" TypeName="BIGINT" Description="A large integer. The signed range is -9223372036854775808 to 9223372036854775807. The unsigned range is 0 to 18446744073709551615." ParamCount="1" OptionCount="2" ParamRequired="0" EditParamsAsString="0" SynonymGroup="0" PhysicalMapping="0" PhysicalTypeName="" >
<PARAMS>
<PARAM Name="length" />
</PARAMS>
<OPTIONS>
<OPTION Name="UNSIGNED" Default="0" />
<OPTION Name="ZEROFILL" Default="0" />
</OPTIONS>
</DATATYPE>
<DATATYPE ID="7" IDGroup="0" TypeName="FLOAT" Description="A small (single-precision) floating-point number. Cannot be unsigned. Allowable values are -3.402823466E+38 to -1.175494351E-38, 0, and 1.175494351E-38 to 3.402823466E+38." ParamCount="1" OptionCount="1" ParamRequired="1" EditParamsAsString="0" SynonymGroup="0" PhysicalMapping="0" PhysicalTypeName="" >
<PARAMS>
<PARAM Name="precision" />
</PARAMS>
<OPTIONS>
<OPTION Name="ZEROFILL" Default="0" />
</OPTIONS>
</DATATYPE>
<DATATYPE ID="8" IDGroup="0" TypeName="FLOAT" Description="A small (single-precision) floating-point number. Cannot be unsigned. Allowable values are -3.402823466E+38 to -1.175494351E-38, 0, and 1.175494351E-38 to 3.402823466E+38." ParamCount="2" OptionCount="1" ParamRequired="0" EditParamsAsString="0" SynonymGroup="0" PhysicalMapping="0" PhysicalTypeName="" >
<PARAMS>
<PARAM Name="length" />
<PARAM Name="decimals" />
</PARAMS>
<OPTIONS>
<OPTION Name="ZEROFILL" Default="0" />
</OPTIONS>
</DATATYPE>
<DATATYPE ID="9" IDGroup="0" TypeName="DOUBLE" Description="A normal-size (double-precision) floating-point number. Cannot be unsigned. Allowable values are -1.7976931348623157E+308 to -2.2250738585072014E-308, 0, and 2.2250738585072014E-308 to 1.7976931348623157E+308." ParamCount="2" OptionCount="1" ParamRequired="0" EditParamsAsString="0" SynonymGroup="2" PhysicalMapping="0" PhysicalTypeName="" >
<PARAMS>
<PARAM Name="length" />
<PARAM Name="decimals" />
</PARAMS>
<OPTIONS>
<OPTION Name="ZEROFILL" Default="0" />
</OPTIONS>
</DATATYPE>
<DATATYPE ID="10" IDGroup="0" TypeName="DOUBLE PRECISION" Description="This is a synonym for DOUBLE." ParamCount="2" OptionCount="1" ParamRequired="0" EditParamsAsString="0" SynonymGroup="2" PhysicalMapping="0" PhysicalTypeName="" >
<PARAMS>
<PARAM Name="length" />
<PARAM Name="decimals" />
</PARAMS>
<OPTIONS>
<OPTION Name="ZEROFILL" Default="0" />
</OPTIONS>
</DATATYPE>
<DATATYPE ID="11" IDGroup="0" TypeName="REAL" Description="This is a synonym for DOUBLE." ParamCount="2" OptionCount="1" ParamRequired="0" EditParamsAsString="0" SynonymGroup="2" PhysicalMapping="0" PhysicalTypeName="" >
<PARAMS>
<PARAM Name="length" />
<PARAM Name="decimals" />
</PARAMS>
<OPTIONS>
<OPTION Name="ZEROFILL" Default="0" />
</OPTIONS>
</DATATYPE>
<DATATYPE ID="12" IDGroup="0" TypeName="DECIMAL" Description="An unpacked floating-point number. Cannot be unsigned. Behaves like a CHAR column." ParamCount="2" OptionCount="1" ParamRequired="0" EditParamsAsString="0" SynonymGroup="3" PhysicalMapping="0" PhysicalTypeName="" >
<PARAMS>
<PARAM Name="length" />
<PARAM Name="decimals" />
</PARAMS>
<OPTIONS>
<OPTION Name="ZEROFILL" Default="0" />
</OPTIONS>
</DATATYPE>
<DATATYPE ID="13" IDGroup="0" TypeName="NUMERIC" Description="This is a synonym for DECIMAL." ParamCount="2" OptionCount="1" ParamRequired="1" EditParamsAsString="0" SynonymGroup="3" PhysicalMapping="0" PhysicalTypeName="" >
<PARAMS>
<PARAM Name="length" />
<PARAM Name="decimals" />
</PARAMS>
<OPTIONS>
<OPTION Name="ZEROFILL" Default="0" />
</OPTIONS>
</DATATYPE>
<DATATYPE ID="14" IDGroup="1" TypeName="DATE" Description="A date. The supported range is \a1000-01-01\a to \a9999-12-31\a." ParamCount="0" OptionCount="0" ParamRequired="0" EditParamsAsString="0" SynonymGroup="0" PhysicalMapping="0" PhysicalTypeName="" >
</DATATYPE>
<DATATYPE ID="15" IDGroup="1" TypeName="DATETIME" Description="A date and time combination. The supported range is \a1000-01-01 00:00:00\a to \a9999-12-31 23:59:59\a." ParamCount="0" OptionCount="0" ParamRequired="0" EditParamsAsString="0" SynonymGroup="0" PhysicalMapping="0" PhysicalTypeName="" >
</DATATYPE>
<DATATYPE ID="16" IDGroup="1" TypeName="TIMESTAMP" Description="A timestamp. The range is \a1970-01-01 00:00:00\a to sometime in the year 2037. The length can be 14 (or missing), 12, 10, 8, 6, 4, or 2 representing YYYYMMDDHHMMSS, ... , YYYYMMDD, ... , YY formats." ParamCount="1" OptionCount="0" ParamRequired="0" EditParamsAsString="0" SynonymGroup="0" PhysicalMapping="0" PhysicalTypeName="" >
<PARAMS>
<PARAM Name="length" />
</PARAMS>
</DATATYPE>
<DATATYPE ID="17" IDGroup="1" TypeName="TIME" Description="A time. The range is \a-838:59:59\a to \a838:59:59\a." ParamCount="0" OptionCount="0" ParamRequired="0" EditParamsAsString="0" SynonymGroup="0" PhysicalMapping="0" PhysicalTypeName="" >
</DATATYPE>
<DATATYPE ID="18" IDGroup="1" TypeName="YEAR" Description="A year in 2- or 4-digit format (default is 4-digit)." ParamCount="1" OptionCount="0" ParamRequired="0" EditParamsAsString="0" SynonymGroup="0" PhysicalMapping="0" PhysicalTypeName="" >
<PARAMS>
<PARAM Name="length" />
</PARAMS>
</DATATYPE>
<DATATYPE ID="19" IDGroup="2" TypeName="CHAR" Description="A fixed-length string (1 to 255 characters) that is always right-padded with spaces to the specified length when stored. values are sorted and compared in case-insensitive fashion according to the default character set unless the BINARY keyword is given." ParamCount="1" OptionCount="1" ParamRequired="1" EditParamsAsString="0" SynonymGroup="0" PhysicalMapping="0" PhysicalTypeName="" >
<PARAMS>
<PARAM Name="length" />
</PARAMS>
<OPTIONS>
<OPTION Name="BINARY" Default="0" />
</OPTIONS>
</DATATYPE>
<DATATYPE ID="20" IDGroup="2" TypeName="VARCHAR" Description="A variable-length string (1 to 255 characters). Values are sorted and compared in case-sensitive fashion unless the BINARY keyword is given." ParamCount="1" OptionCount="1" ParamRequired="1" EditParamsAsString="0" SynonymGroup="0" PhysicalMapping="0" PhysicalTypeName="" >
<PARAMS>
<PARAM Name="length" />
</PARAMS>
<OPTIONS>
<OPTION Name="BINARY" Default="0" />
</OPTIONS>
</DATATYPE>
<DATATYPE ID="21" IDGroup="2" TypeName="BIT" Description="This is a synonym for CHAR(1)." ParamCount="0" OptionCount="0" ParamRequired="0" EditParamsAsString="0" SynonymGroup="0" PhysicalMapping="0" PhysicalTypeName="" >
</DATATYPE>
<DATATYPE ID="22" IDGroup="2" TypeName="BOOL" Description="This is a synonym for CHAR(1)." ParamCount="0" OptionCount="0" ParamRequired="0" EditParamsAsString="0" SynonymGroup="0" PhysicalMapping="0" PhysicalTypeName="" >
</DATATYPE>
<DATATYPE ID="23" IDGroup="3" TypeName="TINYBLOB" Description="A column maximum length of 255 (2^8 - 1) characters. Values are sorted and compared in case-sensitive fashion." ParamCount="0" OptionCount="0" ParamRequired="0" EditParamsAsString="0" SynonymGroup="0" PhysicalMapping="0" PhysicalTypeName="" >
</DATATYPE>
<DATATYPE ID="24" IDGroup="3" TypeName="BLOB" Description="A column maximum length of 65535 (2^16 - 1) characters. Values are sorted and compared in case-sensitive fashion." ParamCount="0" OptionCount="0" ParamRequired="0" EditParamsAsString="0" SynonymGroup="0" PhysicalMapping="0" PhysicalTypeName="" >
</DATATYPE>
<DATATYPE ID="25" IDGroup="3" TypeName="MEDIUMBLOB" Description="A column maximum length of 16777215 (2^24 - 1) characters. Values are sorted and compared in case-sensitive fashion." ParamCount="0" OptionCount="0" ParamRequired="0" EditParamsAsString="0" SynonymGroup="0" PhysicalMapping="0" PhysicalTypeName="" >
</DATATYPE>
<DATATYPE ID="26" IDGroup="3" TypeName="LONGBLOB" Description="A column maximum length of 4294967295 (2^32 - 1) characters. Values are sorted and compared in case-sensitive fashion." ParamCount="0" OptionCount="0" ParamRequired="0" EditParamsAsString="0" SynonymGroup="0" PhysicalMapping="0" PhysicalTypeName="" >
</DATATYPE>
<DATATYPE ID="27" IDGroup="3" TypeName="TINYTEXT" Description="A column maximum length of 255 (2^8 - 1) characters." ParamCount="0" OptionCount="0" ParamRequired="0" EditParamsAsString="0" SynonymGroup="0" PhysicalMapping="0" PhysicalTypeName="" >
</DATATYPE>
<DATATYPE ID="28" IDGroup="3" TypeName="TEXT" Description="A column maximum length of 65535 (2^16 - 1) characters." ParamCount="0" OptionCount="0" ParamRequired="0" EditParamsAsString="0" SynonymGroup="0" PhysicalMapping="0" PhysicalTypeName="" >
</DATATYPE>
<DATATYPE ID="29" IDGroup="3" TypeName="MEDIUMTEXT" Description="A column maximum length of 16777215 (2^24 - 1) characters." ParamCount="0" OptionCount="0" ParamRequired="0" EditParamsAsString="0" SynonymGroup="0" PhysicalMapping="0" PhysicalTypeName="" >
</DATATYPE>
<DATATYPE ID="30" IDGroup="3" TypeName="LONGTEXT" Description="A column maximum length of 4294967295 (2^32 - 1) characters." ParamCount="0" OptionCount="0" ParamRequired="0" EditParamsAsString="0" SynonymGroup="0" PhysicalMapping="0" PhysicalTypeName="" >
</DATATYPE>
<DATATYPE ID="31" IDGroup="3" TypeName="ENUM" Description="An enumeration. A string object that can have only one value, chosen from the list of values." ParamCount="1" OptionCount="0" ParamRequired="1" EditParamsAsString="1" SynonymGroup="0" PhysicalMapping="0" PhysicalTypeName="" >
<PARAMS>
<PARAM Name="values" />
</PARAMS>
</DATATYPE>
<DATATYPE ID="32" IDGroup="3" TypeName="SET" Description="A set. A string object that can have zero or more values, each of which must be chosen from the list of values." ParamCount="1" OptionCount="0" ParamRequired="1" EditParamsAsString="1" SynonymGroup="0" PhysicalMapping="0" PhysicalTypeName="" >
<PARAMS>
<PARAM Name="values" />
</PARAMS>
</DATATYPE>
<DATATYPE ID="33" IDGroup="4" TypeName="Varchar(20)" Description="" ParamCount="0" OptionCount="1" ParamRequired="0" EditParamsAsString="0" SynonymGroup="0" PhysicalMapping="0" PhysicalTypeName="" >
<OPTIONS>
<OPTION Name="BINARY" Default="0" />
</OPTIONS>
</DATATYPE>
<DATATYPE ID="34" IDGroup="4" TypeName="Varchar(45)" Description="" ParamCount="0" OptionCount="1" ParamRequired="0" EditParamsAsString="0" SynonymGroup="0" PhysicalMapping="0" PhysicalTypeName="" >
<OPTIONS>
<OPTION Name="BINARY" Default="0" />
</OPTIONS>
</DATATYPE>
<DATATYPE ID="35" IDGroup="4" TypeName="Varchar(255)" Description="" ParamCount="0" OptionCount="1" ParamRequired="0" EditParamsAsString="0" SynonymGroup="0" PhysicalMapping="0" PhysicalTypeName="" >
<OPTIONS>
<OPTION Name="BINARY" Default="0" />
</OPTIONS>
</DATATYPE>
<DATATYPE ID="36" IDGroup="5" TypeName="GEOMETRY" Description="Geographic Datatype" ParamCount="0" OptionCount="0" ParamRequired="0" EditParamsAsString="0" SynonymGroup="0" PhysicalMapping="0" PhysicalTypeName="" >
</DATATYPE>
<DATATYPE ID="38" IDGroup="5" TypeName="LINESTRING" Description="Geographic Datatype" ParamCount="0" OptionCount="0" ParamRequired="0" EditParamsAsString="0" SynonymGroup="0" PhysicalMapping="0" PhysicalTypeName="" >
</DATATYPE>
<DATATYPE ID="39" IDGroup="5" TypeName="POLYGON" Description="Geographic Datatype" ParamCount="0" OptionCount="0" ParamRequired="0" EditParamsAsString="0" SynonymGroup="0" PhysicalMapping="0" PhysicalTypeName="" >
</DATATYPE>
<DATATYPE ID="40" IDGroup="5" TypeName="MULTIPOINT" Description="Geographic Datatype" ParamCount="0" OptionCount="0" ParamRequired="0" EditParamsAsString="0" SynonymGroup="0" PhysicalMapping="0" PhysicalTypeName="" >
</DATATYPE>
<DATATYPE ID="41" IDGroup="5" TypeName="MULTILINESTRING" Description="Geographic Datatype" ParamCount="0" OptionCount="0" ParamRequired="0" EditParamsAsString="0" SynonymGroup="0" PhysicalMapping="0" PhysicalTypeName="" >
</DATATYPE>
<DATATYPE ID="42" IDGroup="5" TypeName="MULTIPOLYGON" Description="Geographic Datatype" ParamCount="0" OptionCount="0" ParamRequired="0" EditParamsAsString="0" SynonymGroup="0" PhysicalMapping="0" PhysicalTypeName="" >
</DATATYPE>
<DATATYPE ID="43" IDGroup="5" TypeName="GEOMETRYCOLLECTION" Description="Geographic Datatype" ParamCount="0" OptionCount="0" ParamRequired="0" EditParamsAsString="0" SynonymGroup="0" PhysicalMapping="0" PhysicalTypeName="" >
</DATATYPE>
</DATATYPES>
<COMMON_DATATYPES>
<COMMON_DATATYPE ID="5" />
<COMMON_DATATYPE ID="8" />
<COMMON_DATATYPE ID="20" />
<COMMON_DATATYPE ID="15" />
<COMMON_DATATYPE ID="22" />
<COMMON_DATATYPE ID="28" />
<COMMON_DATATYPE ID="26" />
<COMMON_DATATYPE ID="33" />
<COMMON_DATATYPE ID="34" />
<COMMON_DATATYPE ID="35" />
</COMMON_DATATYPES>
<TABLEPREFIXES>
<TABLEPREFIX Name="Default (no prefix)" />
</TABLEPREFIXES>
<REGIONCOLORS>
<REGIONCOLOR Color="Red=#FFEEEC" />
<REGIONCOLOR Color="Yellow=#FEFDED" />
<REGIONCOLOR Color="Green=#EAFFE5" />
<REGIONCOLOR Color="Cyan=#ECFDFF" />
<REGIONCOLOR Color="Blue=#F0F1FE" />
<REGIONCOLOR Color="Magenta=#FFEBFA" />
</REGIONCOLORS>
<POSITIONMARKERS>
<POSITIONMARKER ZoomFac="-1.0" X="0" Y="0" />
<POSITIONMARKER ZoomFac="-1.0" X="0" Y="0" />
<POSITIONMARKER ZoomFac="-1.0" X="0" Y="0" />
<POSITIONMARKER ZoomFac="-1.0" X="0" Y="0" />
<POSITIONMARKER ZoomFac="-1.0" X="0" Y="0" />
<POSITIONMARKER ZoomFac="-1.0" X="0" Y="0" />
<POSITIONMARKER ZoomFac="-1.0" X="0" Y="0" />
<POSITIONMARKER ZoomFac="-1.0" X="0" Y="0" />
<POSITIONMARKER ZoomFac="-1.0" X="0" Y="0" />
<POSITIONMARKER ZoomFac="-1.0" X="0" Y="0" />
<POSITIONMARKER ZoomFac="-1.0" X="0" Y="0" />
</POSITIONMARKERS>
</SETTINGS>
<METADATA>
<REGIONS>
</REGIONS>
<TABLES>
<TABLE ID="1000" Tablename="catedra" PrevTableName="Table_01" XPos="270" YPos="116" TableType="0" TablePrefix="0" nmTable="0" Temporary="0" UseStandardInserts="0" StandardInserts="\n" TableOptions="DelayKeyTblUpdates=0\nPackKeys=0\nRowChecksum=0\nRowFormat=0\nUseRaid=0\nRaidType=0\n" Comments="" Collapsed="0" IsLinkedObject="0" IDLinkedModel="-1" Obj_id_Linked="-1" OrderPos="2" >
<COLUMNS>
<COLUMN ID="1002" ColName="cat_codigo" PrevColName="" Pos="0" idDatatype="5" DatatypeParams="" Width="-1" Prec="-1" PrimaryKey="1" NotNull="1" AutoInc="0" IsForeignKey="0" DefaultValue="" Comments="">
<OPTIONSELECTED>
<OPTIONSELECT Value="1" />
<OPTIONSELECT Value="0" />
</OPTIONSELECTED>
</COLUMN>
<COLUMN ID="1004" ColName="cat_nombre" PrevColName="" Pos="1" idDatatype="20" DatatypeParams="(60)" Width="-1" Prec="-1" PrimaryKey="0" NotNull="0" AutoInc="0" IsForeignKey="0" DefaultValue="" Comments="">
<OPTIONSELECTED>
<OPTIONSELECT Value="0" />
</OPTIONSELECTED>
</COLUMN>
<COLUMN ID="14327" ColName="cat_sede" PrevColName="" Pos="2" idDatatype="20" DatatypeParams="(20)" Width="-1" Prec="-1" PrimaryKey="0" NotNull="0" AutoInc="0" IsForeignKey="0" DefaultValue="" Comments="">
<OPTIONSELECTED>
<OPTIONSELECT Value="0" />
</OPTIONSELECTED>
</COLUMN>
</COLUMNS>
<RELATIONS_START>
<RELATION_START ID="1059" />
<RELATION_START ID="1110" />
<RELATION_START ID="14404" />
<RELATION_START ID="14476" />
<RELATION_START ID="14500" />
</RELATIONS_START>
<INDICES>
<INDEX ID="1003" IndexName="PRIMARY" IndexKind="0" FKRefDef_Obj_id="-1">
<INDEXCOLUMNS>
<INDEXCOLUMN idColumn="1002" LengthParam="0" />
</INDEXCOLUMNS>
</INDEX>
</INDICES>
</TABLE>
<TABLE ID="1016" Tablename="ordencab" PrevTableName="Table_04" XPos="665" YPos="276" TableType="0" TablePrefix="0" nmTable="0" Temporary="0" UseStandardInserts="0" StandardInserts="\n" TableOptions="DelayKeyTblUpdates=0\nPackKeys=0\nRowChecksum=0\nRowFormat=0\nUseRaid=0\nRaidType=0\n" Comments="" Collapsed="0" IsLinkedObject="0" IDLinkedModel="-1" Obj_id_Linked="-1" OrderPos="5" >
<COLUMNS>
<COLUMN ID="1018" ColName="ocab_codigo" PrevColName="" Pos="0" idDatatype="20" DatatypeParams="(15)" Width="-1" Prec="-1" PrimaryKey="1" NotNull="1" AutoInc="0" IsForeignKey="0" DefaultValue="" Comments="">
<OPTIONSELECTED>
<OPTIONSELECT Value="0" />
</OPTIONSELECTED>
</COLUMN>
<COLUMN ID="14571" ColName="mod_cod" PrevColName="" Pos="1" idDatatype="5" DatatypeParams="" Width="-1" Prec="-1" PrimaryKey="0" NotNull="0" AutoInc="0" IsForeignKey="1" DefaultValue="" Comments="">
<OPTIONSELECTED>
<OPTIONSELECT Value="1" />
<OPTIONSELECT Value="0" />
</OPTIONSELECTED>
</COLUMN>
<COLUMN ID="14539" ColName="imp_cod" PrevColName="" Pos="1" idDatatype="5" DatatypeParams="" Width="-1" Prec="-1" PrimaryKey="0" NotNull="1" AutoInc="0" IsForeignKey="1" DefaultValue="" Comments="">
<OPTIONSELECTED>
<OPTIONSELECT Value="1" />
<OPTIONSELECT Value="0" />
</OPTIONSELECTED>
</COLUMN>
<COLUMN ID="14471" ColName="pag_codigo" PrevColName="" Pos="1" idDatatype="5" DatatypeParams="" Width="-1" Prec="-1" PrimaryKey="0" NotNull="1" AutoInc="0" IsForeignKey="1" DefaultValue="" Comments="">
<OPTIONSELECTED>
<OPTIONSELECT Value="1" />
<OPTIONSELECT Value="0" />
</OPTIONSELECTED>
</COLUMN>
<COLUMN ID="1114" ColName="usu_cod" PrevColName="" Pos="1" idDatatype="5" DatatypeParams="" Width="-1" Prec="-1" PrimaryKey="0" NotNull="1" AutoInc="0" IsForeignKey="1" DefaultValue="" Comments="">
<OPTIONSELECTED>
<OPTIONSELECT Value="1" />
<OPTIONSELECT Value="0" />
</OPTIONSELECTED>
</COLUMN>
<COLUMN ID="1092" ColName="pro_codigo" PrevColName="" Pos="1" idDatatype="5" DatatypeParams="" Width="-1" Prec="-1" PrimaryKey="0" NotNull="1" AutoInc="0" IsForeignKey="1" DefaultValue="" Comments="">
<OPTIONSELECTED>
<OPTIONSELECT Value="1" />
<OPTIONSELECT Value="0" />
</OPTIONSELECTED>
</COLUMN>
<COLUMN ID="1060" ColName="cat_codigo" PrevColName="" Pos="1" idDatatype="5" DatatypeParams="" Width="-1" Prec="-1" PrimaryKey="0" NotNull="1" AutoInc="0" IsForeignKey="1" DefaultValue="" Comments="">
<OPTIONSELECTED>
<OPTIONSELECT Value="1" />
<OPTIONSELECT Value="0" />
</OPTIONSELECTED>
</COLUMN>
<COLUMN ID="1020" ColName="ocab_fecha" PrevColName="" Pos="1" idDatatype="14" DatatypeParams="" Width="-1" Prec="-1" PrimaryKey="0" NotNull="0" AutoInc="0" IsForeignKey="0" DefaultValue="" Comments="">
<OPTIONSELECTED>
</OPTIONSELECTED>
</COLUMN>
<COLUMN ID="14322" ColName="ocab_plazo_entrega" PrevColName="" Pos="15" idDatatype="14" DatatypeParams="" Width="-1" Prec="-1" PrimaryKey="0" NotNull="0" AutoInc="0" IsForeignKey="0" DefaultValue="" Comments="">
<OPTIONSELECTED>
</OPTIONSELECTED>
</COLUMN>
<COLUMN ID="1022" ColName="ocab_exenta" PrevColName="" Pos="3" idDatatype="7" DatatypeParams="" Width="-1" Prec="-1" PrimaryKey="0" NotNull="0" AutoInc="0" IsForeignKey="0" DefaultValue="" Comments="">
<OPTIONSELECTED>
<OPTIONSELECT Value="0" />
</OPTIONSELECTED>
</COLUMN>
<COLUMN ID="1023" ColName="ocab_gra5" PrevColName="" Pos="4" idDatatype="7" DatatypeParams="" Width="-1" Prec="-1" PrimaryKey="0" NotNull="0" AutoInc="0" IsForeignKey="0" DefaultValue="" Comments="">
<OPTIONSELECTED>
<OPTIONSELECT Value="0" />
</OPTIONSELECTED>
</COLUMN>
<COLUMN ID="1024" ColName="ocab_gra10" PrevColName="" Pos="5" idDatatype="7" DatatypeParams="" Width="-1" Prec="-1" PrimaryKey="0" NotNull="0" AutoInc="0" IsForeignKey="0" DefaultValue="" Comments="">
<OPTIONSELECTED>
<OPTIONSELECT Value="0" />
</OPTIONSELECTED>
</COLUMN>
<COLUMN ID="1025" ColName="ocab_iva5" PrevColName="" Pos="6" idDatatype="7" DatatypeParams="" Width="-1" Prec="-1" PrimaryKey="0" NotNull="0" AutoInc="0" IsForeignKey="0" DefaultValue="" Comments="">
<OPTIONSELECTED>
<OPTIONSELECT Value="0" />
</OPTIONSELECTED>
</COLUMN>
<COLUMN ID="1026" ColName="ocab_iva10" PrevColName="" Pos="7" idDatatype="7" DatatypeParams="" Width="-1" Prec="-1" PrimaryKey="0" NotNull="0" AutoInc="0" IsForeignKey="0" DefaultValue="" Comments="">
<OPTIONSELECTED>
<OPTIONSELECT Value="0" />
</OPTIONSELECTED>
</COLUMN>
<COLUMN ID="1027" ColName="ocab_total" PrevColName="" Pos="8" idDatatype="7" DatatypeParams="" Width="-1" Prec="-1" PrimaryKey="0" NotNull="0" AutoInc="0" IsForeignKey="0" DefaultValue="" Comments="">
<OPTIONSELECTED>
<OPTIONSELECT Value="0" />
</OPTIONSELECTED>
</COLUMN>
<COLUMN ID="1101" ColName="ocab_entrega" PrevColName="" Pos="13" idDatatype="20" DatatypeParams="(50)" Width="-1" Prec="-1" PrimaryKey="0" NotNull="0" AutoInc="0" IsForeignKey="0" DefaultValue="" Comments="">
<OPTIONSELECTED>
<OPTIONSELECT Value="0" />
</OPTIONSELECTED>
</COLUMN>
<COLUMN ID="14474" ColName="ocab_director" PrevColName="" Pos="16" idDatatype="20" DatatypeParams="(50)" Width="-1" Prec="-1" PrimaryKey="0" NotNull="0" AutoInc="0" IsForeignKey="0" DefaultValue="" Comments="">
<OPTIONSELECTED>
<OPTIONSELECT Value="0" />
</OPTIONSELECTED>
</COLUMN>
<COLUMN ID="14475" ColName="ocab_decano" PrevColName="" Pos="17" idDatatype="20" DatatypeParams="(50)" Width="-1" Prec="-1" PrimaryKey="0" NotNull="0" AutoInc="0" IsForeignKey="0" DefaultValue="" Comments="">
<OPTIONSELECTED>
<OPTIONSELECT Value="0" />
</OPTIONSELECTED>
</COLUMN>
<COLUMN ID="14528" ColName="ocab_estado" PrevColName="" Pos="18" idDatatype="19" DatatypeParams="" Width="-1" Prec="-1" PrimaryKey="0" NotNull="0" AutoInc="0" IsForeignKey="0" DefaultValue="" Comments="">
<OPTIONSELECTED>
<OPTIONSELECT Value="0" />
</OPTIONSELECTED>
</COLUMN>
<COLUMN ID="14532" ColName="ocab_contador" PrevColName="" Pos="18" idDatatype="5" DatatypeParams="(30)" Width="-1" Prec="-1" PrimaryKey="0" NotNull="0" AutoInc="0" IsForeignKey="0" DefaultValue="" Comments="">
<OPTIONSELECTED>
<OPTIONSELECT Value="1" />
<OPTIONSELECT Value="0" />
</OPTIONSELECTED>
</COLUMN>
<COLUMN ID="14555" ColName="tipo_presup" PrevColName="" Pos="19" idDatatype="20" DatatypeParams="(20)" Width="-1" Prec="-1" PrimaryKey="0" NotNull="0" AutoInc="0" IsForeignKey="0" DefaultValue="" Comments="">
<OPTIONSELECTED>
<OPTIONSELECT Value="0" />
</OPTIONSELECTED>
</COLUMN>
<COLUMN ID="14556" ColName="programa" PrevColName="" Pos="20" idDatatype="20" DatatypeParams="(20)" Width="-1" Prec="-1" PrimaryKey="0" NotNull="0" AutoInc="0" IsForeignKey="0" DefaultValue="" Comments="">
<OPTIONSELECTED>
<OPTIONSELECT Value="0" />
</OPTIONSELECTED>
</COLUMN>
<COLUMN ID="14557" ColName="sub_prog" PrevColName="" Pos="21" idDatatype="20" DatatypeParams="(20)" Width="-1" Prec="-1" PrimaryKey="0" NotNull="0" AutoInc="0" IsForeignKey="0" DefaultValue="" Comments="">
<OPTIONSELECTED>
<OPTIONSELECT Value="0" />
</OPTIONSELECTED>
</COLUMN>
<COLUMN ID="14558" ColName="proyecto" PrevColName="" Pos="22" idDatatype="20" DatatypeParams="(20)" Width="-1" Prec="-1" PrimaryKey="0" NotNull="0" AutoInc="0" IsForeignKey="0" DefaultValue="" Comments="">
<OPTIONSELECTED>
<OPTIONSELECT Value="0" />
</OPTIONSELECTED>
</COLUMN>
<COLUMN ID="14559" ColName="fuente_finan" PrevColName="" Pos="23" idDatatype="20" DatatypeParams="(20)" Width="-1" Prec="-1" PrimaryKey="0" NotNull="0" AutoInc="0" IsForeignKey="0" DefaultValue="" Comments="">
<OPTIONSELECTED>
<OPTIONSELECT Value="0" />
</OPTIONSELECTED>
</COLUMN>
<COLUMN ID="14560" ColName="org_financ" PrevColName="" Pos="24" idDatatype="20" DatatypeParams="(20)" Width="-1" Prec="-1" PrimaryKey="0" NotNull="0" AutoInc="0" IsForeignKey="0" DefaultValue="" Comments="">
<OPTIONSELECTED>
<OPTIONSELECT Value="0" />
</OPTIONSELECTED>
</COLUMN>
<COLUMN ID="14561" ColName="obj_gasto" PrevColName="" Pos="25" idDatatype="20" DatatypeParams="(20)" Width="-1" Prec="-1" PrimaryKey="0" NotNull="0" AutoInc="0" IsForeignKey="0" DefaultValue="" Comments="">
<OPTIONSELECTED>
<OPTIONSELECT Value="0" />
</OPTIONSELECTED>
</COLUMN>
<COLUMN ID="14562" ColName="cdp" PrevColName="" Pos="26" idDatatype="20" DatatypeParams="(20)" Width="-1" Prec="-1" PrimaryKey="0" NotNull="0" AutoInc="0" IsForeignKey="0" DefaultValue="" Comments="">
<OPTIONSELECTED>
<OPTIONSELECT Value="0" />
</OPTIONSELECTED>
</COLUMN>
<COLUMN ID="14563" ColName="fec_vigencia" PrevColName="" Pos="27" idDatatype="14" DatatypeParams="" Width="-1" Prec="-1" PrimaryKey="0" NotNull="0" AutoInc="0" IsForeignKey="0" DefaultValue="" Comments="">
<OPTIONSELECTED>
</OPTIONSELECTED>
</COLUMN>
<COLUMN ID="14564" ColName="fec_al" PrevColName="" Pos="28" idDatatype="14" DatatypeParams="" Width="-1" Prec="-1" PrimaryKey="0" NotNull="0" AutoInc="0" IsForeignKey="0" DefaultValue="" Comments="">
<OPTIONSELECTED>
</OPTIONSELECTED>
</COLUMN>
<COLUMN ID="14582" ColName="fec_carga" PrevColName="" Pos="30" idDatatype="14" DatatypeParams="" Width="-1" Prec="-1" PrimaryKey="0" NotNull="0" AutoInc="0" IsForeignKey="0" DefaultValue="" Comments="">
<OPTIONSELECTED>
</OPTIONSELECTED>
</COLUMN>
</COLUMNS>
<RELATIONS_START>
<RELATION_START ID="14583" />
</RELATIONS_START>
<RELATIONS_END>
<RELATION_END ID="1059" />
<RELATION_END ID="1091" />
<RELATION_END ID="1113" />
<RELATION_END ID="14470" />
<RELATION_END ID="14538" />
<RELATION_END ID="14570" />
</RELATIONS_END>
<INDICES>
<INDEX ID="1019" IndexName="PRIMARY" IndexKind="0" FKRefDef_Obj_id="-1">
<INDEXCOLUMNS>
<INDEXCOLUMN idColumn="1018" LengthParam="0" />
</INDEXCOLUMNS>
</INDEX>
<INDEX ID="14547" IndexName="ordencab_FKIndex1" IndexKind="1" FKRefDef_Obj_id="1059">
<INDEXCOLUMNS>
<INDEXCOLUMN idColumn="1060" LengthParam="0" />
</INDEXCOLUMNS>
</INDEX>
<INDEX ID="14548" IndexName="ordencab_FKIndex2" IndexKind="1" FKRefDef_Obj_id="1091">
<INDEXCOLUMNS>
<INDEXCOLUMN idColumn="1092" LengthParam="0" />
</INDEXCOLUMNS>
</INDEX>
<INDEX ID="14549" IndexName="ordencab_FKIndex3" IndexKind="1" FKRefDef_Obj_id="1113">
<INDEXCOLUMNS>
<INDEXCOLUMN idColumn="1114" LengthParam="0" />
</INDEXCOLUMNS>
</INDEX>
<INDEX ID="14550" IndexName="ordencab_FKIndex4" IndexKind="1" FKRefDef_Obj_id="14470">
<INDEXCOLUMNS>
<INDEXCOLUMN idColumn="14471" LengthParam="0" />
</INDEXCOLUMNS>
</INDEX>
<INDEX ID="14551" IndexName="ordencab_FKIndex5" IndexKind="1" FKRefDef_Obj_id="14538">
<INDEXCOLUMNS>
<INDEXCOLUMN idColumn="14539" LengthParam="0" />
</INDEXCOLUMNS>
</INDEX>
<INDEX ID="14572" IndexName="ordencab_FKIndex6" IndexKind="1" FKRefDef_Obj_id="14570">
<INDEXCOLUMNS>
<INDEXCOLUMN idColumn="14571" LengthParam="0" />
</INDEXCOLUMNS>
</INDEX>
</INDICES>
</TABLE>
<TABLE ID="1028" Tablename="detalle_oc" PrevTableName="Table_05" XPos="1118" YPos="436" TableType="0" TablePrefix="0" nmTable="0" Temporary="0" UseStandardInserts="0" StandardInserts="\n" TableOptions="DelayKeyTblUpdates=0\nPackKeys=0\nRowChecksum=0\nRowFormat=0\nUseRaid=0\nRaidType=0\n" Comments="" Collapsed="0" IsLinkedObject="0" IDLinkedModel="-1" Obj_id_Linked="-1" OrderPos="6" >
<COLUMNS>
<COLUMN ID="14587" ColName="odet_cod" PrevColName="" Pos="4" idDatatype="5" DatatypeParams="" Width="-1" Prec="-1" PrimaryKey="1" NotNull="1" AutoInc="0" IsForeignKey="0" DefaultValue="" Comments="">
<OPTIONSELECTED>
<OPTIONSELECT Value="1" />
<OPTIONSELECT Value="0" />
</OPTIONSELECTED>
</COLUMN>
<COLUMN ID="14584" ColName="ocab_codigo" PrevColName="" Pos="1" idDatatype="20" DatatypeParams="(15)" Width="-1" Prec="-1" PrimaryKey="0" NotNull="1" AutoInc="0" IsForeignKey="1" DefaultValue="" Comments="">
<OPTIONSELECTED>
<OPTIONSELECT Value="0" />
</OPTIONSELECTED>
</COLUMN>
<COLUMN ID="1032" ColName="odet_cantidad" PrevColName="" Pos="1" idDatatype="5" DatatypeParams="" Width="-1" Prec="-1" PrimaryKey="0" NotNull="0" AutoInc="0" IsForeignKey="0" DefaultValue="" Comments="">
<OPTIONSELECTED>
<OPTIONSELECT Value="1" />
<OPTIONSELECT Value="0" />
</OPTIONSELECTED>
</COLUMN>
<COLUMN ID="14324" ColName="odet_preciouni" PrevColName="" Pos="6" idDatatype="9" DatatypeParams="" Width="-1" Prec="-1" PrimaryKey="0" NotNull="0" AutoInc="0" IsForeignKey="0" DefaultValue="" Comments="">
<OPTIONSELECTED>
<OPTIONSELECT Value="0" />
</OPTIONSELECTED>
</COLUMN>
<COLUMN ID="14553" ColName="odet_descripcion" PrevColName="" Pos="4" idDatatype="20" DatatypeParams="(200)" Width="-1" Prec="-1" PrimaryKey="0" NotNull="0" AutoInc="0" IsForeignKey="0" DefaultValue="" Comments="">
<OPTIONSELECTED>
<OPTIONSELECT Value="0" />
</OPTIONSELECTED>
</COLUMN>
</COLUMNS>
<RELATIONS_END>
<RELATION_END ID="14583" />
</RELATIONS_END>
<INDICES>
<INDEX ID="14588" IndexName="PRIMARY" IndexKind="0" FKRefDef_Obj_id="-1">
<INDEXCOLUMNS>
<INDEXCOLUMN idColumn="14587" LengthParam="0" />
</INDEXCOLUMNS>
</INDEX>
<INDEX ID="14585" IndexName="ordendet_FKIndex1" IndexKind="1" FKRefDef_Obj_id="14583">
<INDEXCOLUMNS>
<INDEXCOLUMN idColumn="14584" LengthParam="0" />
</INDEXCOLUMNS>
</INDEX>
</INDICES>
</TABLE>
<TABLE ID="1069" Tablename="articulo" PrevTableName="Table_08" XPos="1032" YPos="11" TableType="0" TablePrefix="0" nmTable="0" Temporary="0" UseStandardInserts="0" StandardInserts="\n" TableOptions="DelayKeyTblUpdates=0\nPackKeys=0\nRowChecksum=0\nRowFormat=0\nUseRaid=0\nRaidType=0\n" Comments="" Collapsed="0" IsLinkedObject="0" IDLinkedModel="-1" Obj_id_Linked="-1" OrderPos="11" >
<COLUMNS>
<COLUMN ID="1071" ColName="art_codigo" PrevColName="" Pos="0" idDatatype="5" DatatypeParams="" Width="-1" Prec="-1" PrimaryKey="1" NotNull="1" AutoInc="0" IsForeignKey="0" DefaultValue="" Comments="">
<OPTIONSELECTED>
<OPTIONSELECT Value="1" />
<OPTIONSELECT Value="0" />
</OPTIONSELECTED>
</COLUMN>
<COLUMN ID="14477" ColName="cat_codigo" PrevColName="" Pos="1" idDatatype="5" DatatypeParams="" Width="-1" Prec="-1" PrimaryKey="0" NotNull="1" AutoInc="0" IsForeignKey="1" DefaultValue="" Comments="">
<OPTIONSELECTED>
<OPTIONSELECT Value="1" />
<OPTIONSELECT Value="0" />
</OPTIONSELECTED>
</COLUMN>
<COLUMN ID="14408" ColName="tip_cod" PrevColName="" Pos="1" idDatatype="5" DatatypeParams="" Width="-1" Prec="-1" PrimaryKey="0" NotNull="1" AutoInc="0" IsForeignKey="1" DefaultValue="" Comments="">
<OPTIONSELECTED>
<OPTIONSELECT Value="1" />
<OPTIONSELECT Value="0" />
</OPTIONSELECTED>
</COLUMN>
<COLUMN ID="1073" ColName="art_descripcion" PrevColName="" Pos="1" idDatatype="20" DatatypeParams="(200)" Width="-1" Prec="-1" PrimaryKey="0" NotNull="0" AutoInc="0" IsForeignKey="0" DefaultValue="" Comments="">
<OPTIONSELECTED>
<OPTIONSELECT Value="0" />
</OPTIONSELECTED>
</COLUMN>
<COLUMN ID="14393" ColName="art_precio" PrevColName="" Pos="3" idDatatype="9" DatatypeParams="" Width="-1" Prec="-1" PrimaryKey="0" NotNull="0" AutoInc="0" IsForeignKey="0" DefaultValue="" Comments="">
<OPTIONSELECTED>
<OPTIONSELECT Value="0" />
</OPTIONSELECTED>
</COLUMN>
<COLUMN ID="1074" ColName="art_unidad" PrevColName="" Pos="2" idDatatype="20" DatatypeParams="(20)" Width="-1" Prec="-1" PrimaryKey="0" NotNull="0" AutoInc="0" IsForeignKey="0" DefaultValue="" Comments="">
<OPTIONSELECTED>
<OPTIONSELECT Value="0" />
</OPTIONSELECTED>
</COLUMN>
<COLUMN ID="14394" ColName="art_cod_catalogo" PrevColName="" Pos="4" idDatatype="20" DatatypeParams="(50)" Width="-1" Prec="-1" PrimaryKey="0" NotNull="0" AutoInc="0" IsForeignKey="0" DefaultValue="" Comments="">
<OPTIONSELECTED>
<OPTIONSELECT Value="0" />
</OPTIONSELECTED>
</COLUMN>
<COLUMN ID="14395" ColName="art_presentacion" PrevColName="" Pos="5" idDatatype="20" DatatypeParams="(50)" Width="-1" Prec="-1" PrimaryKey="0" NotNull="0" AutoInc="0" IsForeignKey="0" DefaultValue="" Comments="">
<OPTIONSELECTED>
<OPTIONSELECT Value="0" />
</OPTIONSELECTED>
</COLUMN>
<COLUMN ID="14480" ColName="art_impuesto" PrevColName="" Pos="8" idDatatype="20" DatatypeParams="(20)" Width="-1" Prec="-1" PrimaryKey="0" NotNull="0" AutoInc="0" IsForeignKey="0" DefaultValue="" Comments="">
<OPTIONSELECTED>
<OPTIONSELECT Value="0" />
</OPTIONSELECTED>
</COLUMN>
</COLUMNS>
<RELATIONS_END>
<RELATION_END ID="14407" />
<RELATION_END ID="14476" />
</RELATIONS_END>
<INDICES>
<INDEX ID="1072" IndexName="PRIMARY" IndexKind="0" FKRefDef_Obj_id="-1">
<INDEXCOLUMNS>
<INDEXCOLUMN idColumn="1071" LengthParam="0" />
</INDEXCOLUMNS>
</INDEX>
<INDEX ID="14409" IndexName="articulo_FKIndex1" IndexKind="1" FKRefDef_Obj_id="14407">
<INDEXCOLUMNS>
<INDEXCOLUMN idColumn="14408" LengthParam="0" />
</INDEXCOLUMNS>
</INDEX>
<INDEX ID="14478" IndexName="articulo_FKIndex2" IndexKind="1" FKRefDef_Obj_id="14476">
<INDEXCOLUMNS>
<INDEXCOLUMN idColumn="14477" LengthParam="0" />
</INDEXCOLUMNS>
</INDEX>
</INDICES>
</TABLE>
<TABLE ID="1078" Tablename="proveedor" PrevTableName="Table_09" XPos="42" YPos="596" TableType="0" TablePrefix="0" nmTable="0" Temporary="0" UseStandardInserts="0" StandardInserts="\n" TableOptions="DelayKeyTblUpdates=0\nPackKeys=0\nRowChecksum=0\nRowFormat=0\nUseRaid=0\nRaidType=0\n" Comments="" Collapsed="0" IsLinkedObject="0" IDLinkedModel="-1" Obj_id_Linked="-1" OrderPos="13" >
<COLUMNS>
<COLUMN ID="1080" ColName="pro_codigo" PrevColName="" Pos="0" idDatatype="5" DatatypeParams="" Width="-1" Prec="-1" PrimaryKey="1" NotNull="1" AutoInc="1" IsForeignKey="0" DefaultValue="" Comments="">
<OPTIONSELECTED>
<OPTIONSELECT Value="1" />
<OPTIONSELECT Value="0" />
</OPTIONSELECTED>
</COLUMN>
<COLUMN ID="1082" ColName="pro_descripcion" PrevColName="" Pos="1" idDatatype="20" DatatypeParams="(100)" Width="-1" Prec="-1" PrimaryKey="0" NotNull="0" AutoInc="0" IsForeignKey="0" DefaultValue="" Comments="">
<OPTIONSELECTED>
<OPTIONSELECT Value="0" />
</OPTIONSELECTED>
</COLUMN>
<COLUMN ID="1084" ColName="pro_telefono" PrevColName="" Pos="3" idDatatype="20" DatatypeParams="(30)" Width="-1" Prec="-1" PrimaryKey="0" NotNull="0" AutoInc="0" IsForeignKey="0" DefaultValue="" Comments="">
<OPTIONSELECTED>
<OPTIONSELECT Value="0" />
</OPTIONSELECTED>
</COLUMN>
<COLUMN ID="1085" ColName="pro_direccion" PrevColName="" Pos="4" idDatatype="20" DatatypeParams="(200)" Width="-1" Prec="-1" PrimaryKey="0" NotNull="0" AutoInc="0" IsForeignKey="0" DefaultValue="" Comments="">
<OPTIONSELECTED>
<OPTIONSELECT Value="0" />
</OPTIONSELECTED>
</COLUMN>
<COLUMN ID="1083" ColName="pro_ruc" PrevColName="" Pos="2" idDatatype="20" DatatypeParams="(30)" Width="-1" Prec="-1" PrimaryKey="0" NotNull="0" AutoInc="0" IsForeignKey="0" DefaultValue="" Comments="">
<OPTIONSELECTED>
<OPTIONSELECT Value="0" />
</OPTIONSELECTED>
</COLUMN>
<COLUMN ID="1086" ColName="pro_contacto" PrevColName="" Pos="5" idDatatype="20" DatatypeParams="(100)" Width="-1" Prec="-1" PrimaryKey="0" NotNull="0" AutoInc="0" IsForeignKey="0" DefaultValue="" Comments="">
<OPTIONSELECTED>
<OPTIONSELECT Value="0" />
</OPTIONSELECTED>
</COLUMN>
</COLUMNS>
<RELATIONS_START>
<RELATION_START ID="1091" />
<RELATION_START ID="14501" />
</RELATIONS_START>
<INDICES>
<INDEX ID="1081" IndexName="PRIMARY" IndexKind="0" FKRefDef_Obj_id="-1">
<INDEXCOLUMNS>
<INDEXCOLUMN idColumn="1080" LengthParam="0" />
</INDEXCOLUMNS>
</INDEX>
</INDICES>
</TABLE>
<TABLE ID="1102" Tablename="usuario" PrevTableName="Table_08" XPos="227" YPos="412" TableType="0" TablePrefix="0" nmTable="0" Temporary="0" UseStandardInserts="0" StandardInserts="\n" TableOptions="DelayKeyTblUpdates=0\nPackKeys=0\nRowChecksum=0\nRowFormat=0\nUseRaid=0\nRaidType=0\n" Comments="" Collapsed="0" IsLinkedObject="0" IDLinkedModel="-1" Obj_id_Linked="-1" OrderPos="15" >
<COLUMNS>
<COLUMN ID="1104" ColName="usu_cod" PrevColName="" Pos="0" idDatatype="5" DatatypeParams="" Width="-1" Prec="-1" PrimaryKey="1" NotNull="1" AutoInc="1" IsForeignKey="0" DefaultValue="" Comments="">
<OPTIONSELECTED>
<OPTIONSELECT Value="1" />
<OPTIONSELECT Value="0" />
</OPTIONSELECTED>
</COLUMN>
<COLUMN ID="1111" ColName="cat_codigo" PrevColName="" Pos="1" idDatatype="5" DatatypeParams="" Width="-1" Prec="-1" PrimaryKey="0" NotNull="1" AutoInc="0" IsForeignKey="1" DefaultValue="" Comments="">
<OPTIONSELECTED>
<OPTIONSELECT Value="1" />
<OPTIONSELECT Value="0" />
</OPTIONSELECTED>
</COLUMN>
<COLUMN ID="1106" ColName="usu_nom" PrevColName="" Pos="1" idDatatype="20" DatatypeParams="(50)" Width="-1" Prec="-1" PrimaryKey="0" NotNull="0" AutoInc="0" IsForeignKey="0" DefaultValue="" Comments="">
<OPTIONSELECTED>
<OPTIONSELECT Value="0" />
</OPTIONSELECTED>
</COLUMN>
<COLUMN ID="1107" ColName="usu_ape" PrevColName="" Pos="2" idDatatype="20" DatatypeParams="(50)" Width="-1" Prec="-1" PrimaryKey="0" NotNull="0" AutoInc="0" IsForeignKey="0" DefaultValue="" Comments="">
<OPTIONSELECTED>
<OPTIONSELECT Value="0" />
</OPTIONSELECTED>
</COLUMN>
<COLUMN ID="1108" ColName="usu_user" PrevColName="" Pos="3" idDatatype="20" DatatypeParams="(30)" Width="-1" Prec="-1" PrimaryKey="0" NotNull="0" AutoInc="0" IsForeignKey="0" DefaultValue="" Comments="">
<OPTIONSELECTED>
<OPTIONSELECT Value="0" />
</OPTIONSELECTED>
</COLUMN>
<COLUMN ID="1109" ColName="usu_pas" PrevColName="" Pos="4" idDatatype="20" DatatypeParams="(30)" Width="-1" Prec="-1" PrimaryKey="0" NotNull="0" AutoInc="0" IsForeignKey="0" DefaultValue="" Comments="">
<OPTIONSELECTED>
<OPTIONSELECT Value="0" />
</OPTIONSELECTED>
</COLUMN>
</COLUMNS>
<RELATIONS_START>
<RELATION_START ID="1113" />
</RELATIONS_START>
<RELATIONS_END>
<RELATION_END ID="1110" />
</RELATIONS_END>
<INDICES>
<INDEX ID="1105" IndexName="PRIMARY" IndexKind="0" FKRefDef_Obj_id="-1">
<INDEXCOLUMNS>
<INDEXCOLUMN idColumn="1104" LengthParam="0" />
</INDEXCOLUMNS>
</INDEX>
<INDEX ID="1112" IndexName="usuario_FKIndex1" IndexKind="1" FKRefDef_Obj_id="1110">
<INDEXCOLUMNS>
<INDEXCOLUMN idColumn="1111" LengthParam="0" />
</INDEXCOLUMNS>
</INDEX>
</INDICES>
</TABLE>
<TABLE ID="14399" Tablename="tipo_articulo" PrevTableName="Table_09" XPos="693" YPos="114" TableType="0" TablePrefix="0" nmTable="0" Temporary="0" UseStandardInserts="0" StandardInserts="\n" TableOptions="DelayKeyTblUpdates=0\nPackKeys=0\nRowChecksum=0\nRowFormat=0\nUseRaid=0\nRaidType=0\n" Comments="" Collapsed="0" IsLinkedObject="0" IDLinkedModel="-1" Obj_id_Linked="-1" OrderPos="18" >
<COLUMNS>
<COLUMN ID="14401" ColName="tip_cod" PrevColName="" Pos="0" idDatatype="5" DatatypeParams="" Width="-1" Prec="-1" PrimaryKey="1" NotNull="1" AutoInc="0" IsForeignKey="0" DefaultValue="" Comments="">
<OPTIONSELECTED>
<OPTIONSELECT Value="1" />
<OPTIONSELECT Value="0" />
</OPTIONSELECTED>
</COLUMN>
<COLUMN ID="14405" ColName="cat_codigo" PrevColName="" Pos="1" idDatatype="5" DatatypeParams="" Width="-1" Prec="-1" PrimaryKey="0" NotNull="1" AutoInc="0" IsForeignKey="1" DefaultValue="" Comments="">
<OPTIONSELECTED>
<OPTIONSELECT Value="1" />
<OPTIONSELECT Value="0" />
</OPTIONSELECTED>
</COLUMN>
<COLUMN ID="14403" ColName="tip_descripcion" PrevColName="" Pos="1" idDatatype="20" DatatypeParams="(40)" Width="-1" Prec="-1" PrimaryKey="0" NotNull="0" AutoInc="0" IsForeignKey="0" DefaultValue="" Comments="">
<OPTIONSELECTED>
<OPTIONSELECT Value="0" />
</OPTIONSELECTED>
</COLUMN>
</COLUMNS>
<RELATIONS_START>
<RELATION_START ID="14407" />
</RELATIONS_START>
<RELATIONS_END>
<RELATION_END ID="14404" />
</RELATIONS_END>
<INDICES>
<INDEX ID="14402" IndexName="PRIMARY" IndexKind="0" FKRefDef_Obj_id="-1">
<INDEXCOLUMNS>
<INDEXCOLUMN idColumn="14401" LengthParam="0" />
</INDEXCOLUMNS>
</INDEX>
<INDEX ID="14406" IndexName="tipo_articulo_FKIndex1" IndexKind="1" FKRefDef_Obj_id="14404">
<INDEXCOLUMNS>
<INDEXCOLUMN idColumn="14405" LengthParam="0" />
</INDEXCOLUMNS>
</INDEX>
</INDICES>
</TABLE>
<TABLE ID="14465" Tablename="forma_pago" PrevTableName="Table_10" XPos="339" YPos="293" TableType="0" TablePrefix="0" nmTable="0" Temporary="0" UseStandardInserts="0" StandardInserts="\n" TableOptions="DelayKeyTblUpdates=0\nPackKeys=0\nRowChecksum=0\nRowFormat=0\nUseRaid=0\nRaidType=0\n" Comments="" Collapsed="0" IsLinkedObject="0" IDLinkedModel="-1" Obj_id_Linked="-1" OrderPos="21" >
<COLUMNS>
<COLUMN ID="14467" ColName="pag_codigo" PrevColName="" Pos="0" idDatatype="5" DatatypeParams="" Width="-1" Prec="-1" PrimaryKey="1" NotNull="1" AutoInc="0" IsForeignKey="0" DefaultValue="" Comments="">
<OPTIONSELECTED>
<OPTIONSELECT Value="1" />
<OPTIONSELECT Value="0" />
</OPTIONSELECTED>
</COLUMN>
<COLUMN ID="14469" ColName="pag_descripcion" PrevColName="" Pos="1" idDatatype="20" DatatypeParams="(50)" Width="-1" Prec="-1" PrimaryKey="0" NotNull="0" AutoInc="0" IsForeignKey="0" DefaultValue="" Comments="">
<OPTIONSELECTED>
<OPTIONSELECT Value="0" />
</OPTIONSELECTED>
</COLUMN>
</COLUMNS>
<RELATIONS_START>
<RELATION_START ID="14470" />
</RELATIONS_START>
<INDICES>
<INDEX ID="14468" IndexName="PRIMARY" IndexKind="0" FKRefDef_Obj_id="-1">
<INDEXCOLUMNS>
<INDEXCOLUMN idColumn="14467" LengthParam="0" />
</INDEXCOLUMNS>
</INDEX>
</INDICES>
</TABLE>
<TABLE ID="14499" Tablename="catedra_proveedor" PrevTableName="" XPos="16" YPos="350" TableType="0" TablePrefix="0" nmTable="1" Temporary="0" UseStandardInserts="0" StandardInserts="\n" TableOptions="DelayKeyTblUpdates=0\nPackKeys=0\nRowChecksum=0\nRowFormat=0\nUseRaid=0\nRaidType=0\n" Comments="" Collapsed="0" IsLinkedObject="0" IDLinkedModel="-1" Obj_id_Linked="-1" OrderPos="20" >
<COLUMNS>
<COLUMN ID="14502" ColName="cat_codigo" PrevColName="" Pos="1" idDatatype="5" DatatypeParams="" Width="-1" Prec="-1" PrimaryKey="1" NotNull="1" AutoInc="0" IsForeignKey="1" DefaultValue="" Comments="">
<OPTIONSELECTED>
<OPTIONSELECT Value="1" />
<OPTIONSELECT Value="0" />
</OPTIONSELECTED>
</COLUMN>
<COLUMN ID="14504" ColName="pro_codigo" PrevColName="" Pos="1" idDatatype="5" DatatypeParams="" Width="-1" Prec="-1" PrimaryKey="1" NotNull="1" AutoInc="0" IsForeignKey="1" DefaultValue="" Comments="">
<OPTIONSELECTED>
<OPTIONSELECT Value="1" />
<OPTIONSELECT Value="0" />
</OPTIONSELECTED>
</COLUMN>
</COLUMNS>
<RELATIONS_END>
<RELATION_END ID="14500" />
<RELATION_END ID="14501" />
</RELATIONS_END>
<INDICES>
<INDEX ID="14506" IndexName="PRIMARY" IndexKind="0" FKRefDef_Obj_id="-1">
<INDEXCOLUMNS>
<INDEXCOLUMN idColumn="14502" LengthParam="0" />
<INDEXCOLUMN idColumn="14504" LengthParam="0" />
</INDEXCOLUMNS>
</INDEX>
<INDEX ID="14503" IndexName="catedra_has_proveedor_FKIndex1" IndexKind="1" FKRefDef_Obj_id="14500">
<INDEXCOLUMNS>
<INDEXCOLUMN idColumn="14502" LengthParam="0" />
</INDEXCOLUMNS>
</INDEX>
<INDEX ID="14505" IndexName="catedra_has_proveedor_FKIndex2" IndexKind="1" FKRefDef_Obj_id="14501">
<INDEXCOLUMNS>
<INDEXCOLUMN idColumn="14504" LengthParam="0" />
</INDEXCOLUMNS>
</INDEX>
</INDICES>
</TABLE>
<TABLE ID="14507" Tablename="config_orden" PrevTableName="Table_10" XPos="880" YPos="199" TableType="0" TablePrefix="0" nmTable="0" Temporary="0" UseStandardInserts="0" StandardInserts="\n" TableOptions="DelayKeyTblUpdates=0\nPackKeys=0\nRowChecksum=0\nRowFormat=0\nUseRaid=0\nRaidType=0\n" Comments="" Collapsed="0" IsLinkedObject="0" IDLinkedModel="-1" Obj_id_Linked="-1" OrderPos="23" >
<COLUMNS>
<COLUMN ID="14509" ColName="con_cod" PrevColName="" Pos="0" idDatatype="5" DatatypeParams="" Width="-1" Prec="-1" PrimaryKey="1" NotNull="1" AutoInc="0" IsForeignKey="0" DefaultValue="" Comments="">
<OPTIONSELECTED>
<OPTIONSELECT Value="1" />
<OPTIONSELECT Value="0" />
</OPTIONSELECTED>
</COLUMN>
<COLUMN ID="14511" ColName="fecha_desde" PrevColName="" Pos="1" idDatatype="14" DatatypeParams="" Width="-1" Prec="-1" PrimaryKey="0" NotNull="0" AutoInc="0" IsForeignKey="0" DefaultValue="" Comments="">
<OPTIONSELECTED>
</OPTIONSELECTED>
</COLUMN>
<COLUMN ID="14512" ColName="fecha_hasta" PrevColName="" Pos="2" idDatatype="14" DatatypeParams="" Width="-1" Prec="-1" PrimaryKey="0" NotNull="0" AutoInc="0" IsForeignKey="0" DefaultValue="" Comments="">
<OPTIONSELECTED>
</OPTIONSELECTED>
</COLUMN>
<COLUMN ID="14513" ColName="decano" PrevColName="" Pos="3" idDatatype="20" DatatypeParams="(100)" Width="-1" Prec="-1" PrimaryKey="0" NotNull="0" AutoInc="0" IsForeignKey="0" DefaultValue="" Comments="">
<OPTIONSELECTED>
<OPTIONSELECT Value="0" />
</OPTIONSELECTED>
</COLUMN>
<COLUMN ID="14514" ColName="director" PrevColName="" Pos="4" idDatatype="20" DatatypeParams="(100)" Width="-1" Prec="-1" PrimaryKey="0" NotNull="0" AutoInc="0" IsForeignKey="0" DefaultValue="" Comments="">
<OPTIONSELECTED>
<OPTIONSELECT Value="0" />
</OPTIONSELECTED>
</COLUMN>
</COLUMNS>
<INDICES>
<INDEX ID="14510" IndexName="PRIMARY" IndexKind="0" FKRefDef_Obj_id="-1">
<INDEXCOLUMNS>
<INDEXCOLUMN idColumn="14509" LengthParam="0" />
</INDEXCOLUMNS>
</INDEX>
</INDICES>
</TABLE>
<TABLE ID="14533" Tablename="imputacion" PrevTableName="Table_11" XPos="1089" YPos="628" TableType="0" TablePrefix="0" nmTable="0" Temporary="0" UseStandardInserts="0" StandardInserts="\n" TableOptions="DelayKeyTblUpdates=0\nPackKeys=0\nRowChecksum=0\nRowFormat=0\nUseRaid=0\nRaidType=0\n" Comments="" Collapsed="0" IsLinkedObject="0" IDLinkedModel="-1" Obj_id_Linked="-1" OrderPos="24" >
<COLUMNS>
<COLUMN ID="14535" ColName="imp_cod" PrevColName="" Pos="0" idDatatype="5" DatatypeParams="" Width="-1" Prec="-1" PrimaryKey="1" NotNull="1" AutoInc="0" IsForeignKey="0" DefaultValue="" Comments="">
<OPTIONSELECTED>
<OPTIONSELECT Value="1" />
<OPTIONSELECT Value="0" />
</OPTIONSELECTED>
</COLUMN>
<COLUMN ID="14537" ColName="imp_des" PrevColName="" Pos="1" idDatatype="20" DatatypeParams="(100)" Width="-1" Prec="-1" PrimaryKey="0" NotNull="0" AutoInc="0" IsForeignKey="0" DefaultValue="" Comments="">
<OPTIONSELECTED>
<OPTIONSELECT Value="0" />
</OPTIONSELECTED>
</COLUMN>
</COLUMNS>
<RELATIONS_START>
<RELATION_START ID="14538" />
</RELATIONS_START>
<INDICES>
<INDEX ID="14536" IndexName="PRIMARY" IndexKind="0" FKRefDef_Obj_id="-1">
<INDEXCOLUMNS>
<INDEXCOLUMN idColumn="14535" LengthParam="0" />
</INDEXCOLUMNS>
</INDEX>
</INDICES>
</TABLE>
<TABLE ID="14565" Tablename="modalidad" PrevTableName="Table_12" XPos="353" YPos="716" TableType="0" TablePrefix="0" nmTable="0" Temporary="0" UseStandardInserts="0" StandardInserts="\n" TableOptions="DelayKeyTblUpdates=0\nPackKeys=0\nRowChecksum=0\nRowFormat=0\nUseRaid=0\nRaidType=0\n" Comments="" Collapsed="0" IsLinkedObject="0" IDLinkedModel="-1" Obj_id_Linked="-1" OrderPos="26" >
<COLUMNS>
<COLUMN ID="14567" ColName="mod_cod" PrevColName="" Pos="0" idDatatype="5" DatatypeParams="" Width="-1" Prec="-1" PrimaryKey="1" NotNull="1" AutoInc="0" IsForeignKey="0" DefaultValue="" Comments="">
<OPTIONSELECTED>
<OPTIONSELECT Value="1" />
<OPTIONSELECT Value="0" />
</OPTIONSELECTED>
</COLUMN>
<COLUMN ID="14579" ColName="tip_cod" PrevColName="" Pos="1" idDatatype="5" DatatypeParams="" Width="-1" Prec="-1" PrimaryKey="0" NotNull="0" AutoInc="0" IsForeignKey="1" DefaultValue="" Comments="">
<OPTIONSELECTED>
<OPTIONSELECT Value="1" />
<OPTIONSELECT Value="0" />
</OPTIONSELECTED>
</COLUMN>
<COLUMN ID="14569" ColName="mod_des" PrevColName="" Pos="1" idDatatype="20" DatatypeParams="(30)" Width="-1" Prec="-1" PrimaryKey="0" NotNull="0" AutoInc="0" IsForeignKey="0" DefaultValue="" Comments="">
<OPTIONSELECTED>
<OPTIONSELECT Value="0" />
</OPTIONSELECTED>
</COLUMN>
</COLUMNS>
<RELATIONS_START>
<RELATION_START ID="14570" />
</RELATIONS_START>
<RELATIONS_END>
<RELATION_END ID="14578" />
</RELATIONS_END>
<INDICES>
<INDEX ID="14568" IndexName="PRIMARY" IndexKind="0" FKRefDef_Obj_id="-1">
<INDEXCOLUMNS>
<INDEXCOLUMN idColumn="14567" LengthParam="0" />
</INDEXCOLUMNS>
</INDEX>
<INDEX ID="14580" IndexName="modalidad_FKIndex1" IndexKind="1" FKRefDef_Obj_id="14578">
<INDEXCOLUMNS>
<INDEXCOLUMN idColumn="14579" LengthParam="0" />
</INDEXCOLUMNS>
</INDEX>
</INDICES>
</TABLE>
<TABLE ID="14573" Tablename="tipo_modalidad" PrevTableName="Table_13" XPos="76" YPos="745" TableType="0" TablePrefix="0" nmTable="0" Temporary="0" UseStandardInserts="0" StandardInserts="\n" TableOptions="DelayKeyTblUpdates=0\nPackKeys=0\nRowChecksum=0\nRowFormat=0\nUseRaid=0\nRaidType=0\n" Comments="" Collapsed="0" IsLinkedObject="0" IDLinkedModel="-1" Obj_id_Linked="-1" OrderPos="28" >
<COLUMNS>
<COLUMN ID="14575" ColName="tip_cod" PrevColName="" Pos="0" idDatatype="5" DatatypeParams="" Width="-1" Prec="-1" PrimaryKey="1" NotNull="1" AutoInc="0" IsForeignKey="0" DefaultValue="" Comments="">
<OPTIONSELECTED>
<OPTIONSELECT Value="1" />
<OPTIONSELECT Value="0" />
</OPTIONSELECTED>
</COLUMN>
<COLUMN ID="14577" ColName="tip_des" PrevColName="" Pos="1" idDatatype="20" DatatypeParams="(50)" Width="-1" Prec="-1" PrimaryKey="0" NotNull="0" AutoInc="0" IsForeignKey="0" DefaultValue="" Comments="">
<OPTIONSELECTED>
<OPTIONSELECT Value="0" />
</OPTIONSELECTED>
</COLUMN>
</COLUMNS>
<RELATIONS_START>
<RELATION_START ID="14578" />
</RELATIONS_START>
<INDICES>
<INDEX ID="14576" IndexName="PRIMARY" IndexKind="0" FKRefDef_Obj_id="-1">
<INDEXCOLUMNS>
<INDEXCOLUMN idColumn="14575" LengthParam="0" />
</INDEXCOLUMNS>
</INDEX>
</INDICES>
</TABLE>
</TABLES>
<RELATIONS>
<RELATION ID="1059" RelationName="Rel_07" Kind="2" SrcTable="1000" DestTable="1016" FKFields="cat_codigo=cat_codigo\n" FKFieldsComments="\n" relDirection="2" MidOffset="0" OptionalStart="0" OptionalEnd="0" CaptionOffsetX="0" CaptionOffsetY="0" StartIntervalOffsetX="0" StartIntervalOffsetY="0" EndIntervalOffsetX="0" EndIntervalOffsetY="0" CreateRefDef="1" Invisible="0" RefDef="Matching=0\nOnDelete=3\nOnUpdate=3\n" Comments="" FKRefDefIndex_Obj_id="14547" Splitted="0" IsLinkedObject="0" IDLinkedModel="-1" Obj_id_Linked="-1" OrderPos="8" />
<RELATION ID="1091" RelationName="Rel_12" Kind="2" SrcTable="1078" DestTable="1016" FKFields="pro_codigo=pro_codigo\n" FKFieldsComments="\n" relDirection="2" MidOffset="0" OptionalStart="0" OptionalEnd="0" CaptionOffsetX="0" CaptionOffsetY="0" StartIntervalOffsetX="0" StartIntervalOffsetY="0" EndIntervalOffsetX="0" EndIntervalOffsetY="0" CreateRefDef="1" Invisible="0" RefDef="Matching=0\nOnDelete=3\nOnUpdate=3\n" Comments="" FKRefDefIndex_Obj_id="14548" Splitted="0" IsLinkedObject="0" IDLinkedModel="-1" Obj_id_Linked="-1" OrderPos="14" />
<RELATION ID="1110" RelationName="Rel_08" Kind="2" SrcTable="1000" DestTable="1102" FKFields="cat_codigo=cat_codigo\n" FKFieldsComments="\n" relDirection="3" MidOffset="0" OptionalStart="0" OptionalEnd="0" CaptionOffsetX="0" CaptionOffsetY="0" StartIntervalOffsetX="0" StartIntervalOffsetY="0" EndIntervalOffsetX="0" EndIntervalOffsetY="0" CreateRefDef="1" Invisible="0" RefDef="Matching=0\nOnDelete=3\nOnUpdate=3\n" Comments="" FKRefDefIndex_Obj_id="1112" Splitted="0" IsLinkedObject="0" IDLinkedModel="-1" Obj_id_Linked="-1" OrderPos="16" />
<RELATION ID="1113" RelationName="Rel_09" Kind="2" SrcTable="1102" DestTable="1016" FKFields="usu_cod=usu_cod\n" FKFieldsComments="\n" relDirection="2" MidOffset="0" OptionalStart="0" OptionalEnd="0" CaptionOffsetX="0" CaptionOffsetY="0" StartIntervalOffsetX="0" StartIntervalOffsetY="0" EndIntervalOffsetX="0" EndIntervalOffsetY="0" CreateRefDef="1" Invisible="0" RefDef="Matching=0\nOnDelete=3\nOnUpdate=3\n" Comments="" FKRefDefIndex_Obj_id="14549" Splitted="0" IsLinkedObject="0" IDLinkedModel="-1" Obj_id_Linked="-1" OrderPos="17" />
<RELATION ID="14404" RelationName="Rel_09" Kind="2" SrcTable="1000" DestTable="14399" FKFields="cat_codigo=cat_codigo\n" FKFieldsComments="\n" relDirection="2" MidOffset="0" OptionalStart="0" OptionalEnd="0" CaptionOffsetX="0" CaptionOffsetY="0" StartIntervalOffsetX="0" StartIntervalOffsetY="0" EndIntervalOffsetX="0" EndIntervalOffsetY="0" CreateRefDef="1" Invisible="0" RefDef="Matching=0\nOnDelete=3\nOnUpdate=3\n" Comments="" FKRefDefIndex_Obj_id="14406" Splitted="0" IsLinkedObject="0" IDLinkedModel="-1" Obj_id_Linked="-1" OrderPos="19" />
<RELATION ID="14407" RelationName="Rel_10" Kind="2" SrcTable="14399" DestTable="1069" FKFields="tip_cod=tip_cod\n" FKFieldsComments="\n" relDirection="2" MidOffset="0" OptionalStart="0" OptionalEnd="0" CaptionOffsetX="0" CaptionOffsetY="0" StartIntervalOffsetX="0" StartIntervalOffsetY="0" EndIntervalOffsetX="0" EndIntervalOffsetY="0" CreateRefDef="1" Invisible="0" RefDef="Matching=0\nOnDelete=3\nOnUpdate=3\n" Comments="" FKRefDefIndex_Obj_id="14409" Splitted="0" IsLinkedObject="0" IDLinkedModel="-1" Obj_id_Linked="-1" OrderPos="20" />
<RELATION ID="14470" RelationName="Rel_11" Kind="2" SrcTable="14465" DestTable="1016" FKFields="pag_codigo=pag_codigo\n" FKFieldsComments="\n" relDirection="2" MidOffset="0" OptionalStart="0" OptionalEnd="0" CaptionOffsetX="0" CaptionOffsetY="0" StartIntervalOffsetX="0" StartIntervalOffsetY="0" EndIntervalOffsetX="0" EndIntervalOffsetY="0" CreateRefDef="1" Invisible="0" RefDef="Matching=0\nOnDelete=3\nOnUpdate=3\n" Comments="" FKRefDefIndex_Obj_id="14550" Splitted="0" IsLinkedObject="0" IDLinkedModel="-1" Obj_id_Linked="-1" OrderPos="22" />
<RELATION ID="14476" RelationName="Rel_12" Kind="2" SrcTable="1000" DestTable="1069" FKFields="cat_codigo=cat_codigo\n" FKFieldsComments="\n" relDirection="2" MidOffset="0" OptionalStart="0" OptionalEnd="0" CaptionOffsetX="0" CaptionOffsetY="0" StartIntervalOffsetX="0" StartIntervalOffsetY="0" EndIntervalOffsetX="0" EndIntervalOffsetY="0" CreateRefDef="1" Invisible="0" RefDef="Matching=0\nOnDelete=3\nOnUpdate=3\n" Comments="" FKRefDefIndex_Obj_id="14478" Splitted="0" IsLinkedObject="0" IDLinkedModel="-1" Obj_id_Linked="-1" OrderPos="19" />
<RELATION ID="14500" RelationName="Rel_11" Kind="1" SrcTable="1000" DestTable="14499" FKFields="cat_codigo=cat_codigo\n" FKFieldsComments="\n" relDirection="4" MidOffset="0" OptionalStart="0" OptionalEnd="0" CaptionOffsetX="0" CaptionOffsetY="0" StartIntervalOffsetX="0" StartIntervalOffsetY="0" EndIntervalOffsetX="0" EndIntervalOffsetY="0" CreateRefDef="1" Invisible="0" RefDef="Matching=0\nOnDelete=3\nOnUpdate=3\n" Comments="" FKRefDefIndex_Obj_id="14503" Splitted="0" IsLinkedObject="0" IDLinkedModel="-1" Obj_id_Linked="-1" OrderPos="21" />
<RELATION ID="14501" RelationName="Rel_12" Kind="1" SrcTable="1078" DestTable="14499" FKFields="pro_codigo=pro_codigo\n" FKFieldsComments="\n" relDirection="1" MidOffset="0" OptionalStart="0" OptionalEnd="0" CaptionOffsetX="0" CaptionOffsetY="0" StartIntervalOffsetX="0" StartIntervalOffsetY="0" EndIntervalOffsetX="0" EndIntervalOffsetY="0" CreateRefDef="1" Invisible="0" RefDef="Matching=0\nOnDelete=3\nOnUpdate=3\n" Comments="" FKRefDefIndex_Obj_id="14505" Splitted="0" IsLinkedObject="0" IDLinkedModel="-1" Obj_id_Linked="-1" OrderPos="22" />
<RELATION ID="14538" RelationName="Rel_13" Kind="2" SrcTable="14533" DestTable="1016" FKFields="imp_cod=imp_cod\n" FKFieldsComments="\n" relDirection="4" MidOffset="0" OptionalStart="0" OptionalEnd="0" CaptionOffsetX="0" CaptionOffsetY="0" StartIntervalOffsetX="0" StartIntervalOffsetY="0" EndIntervalOffsetX="0" EndIntervalOffsetY="0" CreateRefDef="1" Invisible="0" RefDef="Matching=0\nOnDelete=3\nOnUpdate=3\n" Comments="" FKRefDefIndex_Obj_id="14551" Splitted="0" IsLinkedObject="0" IDLinkedModel="-1" Obj_id_Linked="-1" OrderPos="25" />
<RELATION ID="14570" RelationName="Rel_14" Kind="2" SrcTable="14565" DestTable="1016" FKFields="mod_cod=mod_cod\n" FKFieldsComments="\n" relDirection="2" MidOffset="0" OptionalStart="0" OptionalEnd="0" CaptionOffsetX="0" CaptionOffsetY="0" StartIntervalOffsetX="0" StartIntervalOffsetY="0" EndIntervalOffsetX="0" EndIntervalOffsetY="0" CreateRefDef="1" Invisible="0" RefDef="Matching=0\nOnDelete=3\nOnUpdate=3\n" Comments="" FKRefDefIndex_Obj_id="14572" Splitted="0" IsLinkedObject="0" IDLinkedModel="-1" Obj_id_Linked="-1" OrderPos="27" />
<RELATION ID="14578" RelationName="Rel_15" Kind="2" SrcTable="14573" DestTable="14565" FKFields="tip_cod=tip_cod\n" FKFieldsComments="\n" relDirection="2" MidOffset="0" OptionalStart="0" OptionalEnd="0" CaptionOffsetX="0" CaptionOffsetY="0" StartIntervalOffsetX="0" StartIntervalOffsetY="0" EndIntervalOffsetX="0" EndIntervalOffsetY="0" CreateRefDef="1" Invisible="0" RefDef="Matching=0\nOnDelete=3\nOnUpdate=3\n" Comments="" FKRefDefIndex_Obj_id="14580" Splitted="0" IsLinkedObject="0" IDLinkedModel="-1" Obj_id_Linked="-1" OrderPos="29" />
<RELATION ID="14583" RelationName="Rel_16" Kind="2" SrcTable="1016" DestTable="1028" FKFields="ocab_codigo=ocab_codigo\n" FKFieldsComments="\n" relDirection="2" MidOffset="0" OptionalStart="0" OptionalEnd="0" CaptionOffsetX="0" CaptionOffsetY="0" StartIntervalOffsetX="0" StartIntervalOffsetY="0" EndIntervalOffsetX="0" EndIntervalOffsetY="0" CreateRefDef="1" Invisible="0" RefDef="Matching=0\nOnDelete=3\nOnUpdate=3\n" Comments="" FKRefDefIndex_Obj_id="14585" Splitted="0" IsLinkedObject="0" IDLinkedModel="-1" Obj_id_Linked="-1" OrderPos="28" />
</RELATIONS>
<NOTES>
</NOTES>
<IMAGES>
</IMAGES>
</METADATA>
<PLUGINDATA>
<PLUGINDATARECORDS>
</PLUGINDATARECORDS>
</PLUGINDATA>
<QUERYDATA>
<QUERYRECORDS>
</QUERYRECORDS>
</QUERYDATA>
<LINKEDMODELS>
</LINKEDMODELS>
</DBMODEL>
